MANIFEST.in
README.rst
setup.py
scrapyrwiki/__init__.py
scrapyrwiki/helpers.py
scrapyrwiki/pipelines.py
scrapyrwiki/test_helpers.py
scrapyrwiki.egg-info/PKG-INFO
scrapyrwiki.egg-info/SOURCES.txt
scrapyrwiki.egg-info/dependency_links.txt
scrapyrwiki.egg-info/requires.txt
scrapyrwiki.egg-info/top_level.txt
scrapyrwiki.egg-info/zip-safe