Metadata-Version: 1.1
Name: scrapyrwiki
Version: 0.2
Summary: A collection of helpers for running Scrapy in ScraperWiki
Home-page: http://github.com/SpazioDati/scrapyrwiki
Author: SpazioDati
Author-email: hello@spaziodati.eu
License: BSD
Platform: UNKNOWN
Classifier: Development Status :: 3 - Alpha
Classifier: Environment :: Console
Classifier: Intended Audience :: Developers
Classifier: License :: OSI Approved :: BSD License
Classifier: Operating System :: OS Independent
Classifier: Programming Language :: Python
Classifier: Topic :: Utilities
